[
  {
    "_id": "5e978d4129e3c40e103706c3",
    "name": "wash",
    "garage": "5e7a8adfdf14bc31c86b8485",
    "duration": 30,
    "price": 13
  },
  {
    "_id": "5e978d4129e3c40e103706c4",
    "name": "wheel",
    "garage": "5e7a8adfdf14bc31c86b8484",
    "duration": 30,
    "price": 13
  },
  {
    "_id": "5e978d4129e3c40e103706c5",
    "name": "mechanic",
    "garage": "5e7a8adfdf14bc31c86b8483",
    "duration": 25,
    "price": 13
  },
  {
    "_id": "5e978d4129e3c40e103706c6",
    "name": "oilChange",
    "garage": "5e7a8adfdf14bc31c86b8485",
    "duration": 35,
    "price": 50
  },
  {
    "_id": "5e978d4129e3c40e103706c7",
    "name": "oilChange",
    "garage": "5e7a8adfdf14bc31c86b8484",
    "duration": 25,
    "price": 40
  },
  {
    "_id": "5e978d4129e3c40e103706c8",
    "name": "oilChange",
    "garage": "5e7a8adfdf14bc31c86b8483",
    "duration": 30,
    "price": 25
  }
]
